{
    "type": "DP",
    "total_balance": 100000.34,
    "accounts": [
        {
            "id": "80000072",
            "type_code": 1,
            "type_description": "Interest Checking",
            "name": "PERSONAL CHECKING",
            "nick_name": "TEST",
            "balance": 60000,
            "balance_as_of_date": "2019-03-25T10:41:00",
            "created_date": "2019-01-22T14:53:38"
        },
        {
            "id": "68000042",
            "type_code": 41,
            "type_description": "Savings",
            "name": "PERSONAL SAVINGS",
            "nick_name": "Fun fund",
            "balance": 40000.34,
            "balance_as_of_date": "2019-03-25T10:41:00",
            "created_date": "2019-03-08T08:21:41"
        }
    ]
}